README.md
pyproject.toml
setup.cfg
setup.py
openman/__init__.py
openman/cli.py
openman/errors.py
openman/schema_converter.py
openman/utils.py
openman/mock/__init__.py
openman/mock/fakemock_resolver.py
openman/mock/mock.py
openman/parser/__init__.py
openman/parser/collection.py
openman/parser/folder.py
openman/parser/request.py
openman/parser/requestitem.py
openman/parser/response.py
openman/spec/__init__.py
openman/spec/operation.py
openman/spec/plugins.py
openman/spec/spec.py
openman/spec/collector/__init__.py
openman/spec/collector/response.py
openman_pro.egg-info/PKG-INFO
openman_pro.egg-info/SOURCES.txt
openman_pro.egg-info/dependency_links.txt
openman_pro.egg-info/entry_points.txt
openman_pro.egg-info/not-zip-safe
openman_pro.egg-info/requires.txt
openman_pro.egg-info/top_level.txt