Metadata-Version: 2.1
Name: openman-pro
Version: 0.0.2
Summary: A Postman to OpenAPI spec converter with mocking facilities
Home-page: https://github.com/samcaspus/openman
License: MIT
Keywords: api,openapi,rest,specification,oas,documentation
Platform: UNKNOWN
Classifier: Development Status :: 3 - Alpha
Classifier: Intended Audience :: Developers
Classifier: Topic :: Software Development :: Build Tools
Classifier: License :: OSI Approved :: MIT License
Classifier: Programming Language :: Python :: 3
Classifier: Programming Language :: Python :: 3.5
Classifier: Programming Language :: Python :: 3.6
Requires-Python: >=3.5
